popstore/__init__.py
popstore/popstore.py
popstore-0.1.1.dist-info/METADATA
popstore-0.1.1.dist-info/WHEEL
popstore-0.1.1.dist-info/top_level.txt
popstore-0.1.1.dist-info/RECORD
