Metadata-Version: 2.1
Name: popstore
Version: 0.1.1
Summary: UNKNOWN
Home-page: https://github.com/jesseneverdie/popstore.git
Author: Jesse Kim
Author-email: jesse@nextwith.com
License: UNKNOWN
Platform: UNKNOWN
Classifier: Programming Language :: Python :: 3
Classifier: License :: OSI Approved :: MIT License
Classifier: Operating System :: OS Independent
Requires-Python: >=3.6
